{
  "users": [
    {
      "type": "admin",
      "id": 100000000001,
      "username": "admin_root",
      "firstname": "Carlos",
      "lastname": "Mendoza",
      "password": "Admin@1234"
    },
    {
      "type": "admin",
      "id": 100000000002,
      "username": "admin_sofia",
      "firstname": "Sofia",
      "lastname": "Herrera",
      "password": "Admin@5678"
    },
    {
      "type": "patient",
      "id": 112234567890,
      "username": "jgarcia90",
      "firstname": "Juan",
      "lastname": "Garcia",
      "password": "Pass@1234",
      "email": "jgarcia@gmail.com",
      "birthdate": "1990-04-15",
      "gender": true,
      "phone": 3001234567,
      "address": "Calle 45 # 23-10, Barranquilla"
    },
    {
      "type": "patient",
      "id": 223345678901,
      "username": "mlopez85",
      "firstname": "Maria",
      "lastname": "Lopez",
      "password": "Pass@2345",
      "email": "mlopez@hotmail.com",
      "birthdate": "1985-08-22",
      "gender": false,
      "phone": 3112345678,
      "address": "Carrera 50 # 12-30, Bogota"
    },
    {
      "type": "patient",
      "id": 334456789012,
      "username": "pedro_rm",
      "firstname": "Pedro",
      "lastname": "Ramirez",
      "password": "Pass@3456",
      "email": "pedro@yahoo.com",
      "birthdate": "1998-01-30",
      "gender": true,
      "phone": 3209876543,
      "address": "Avenida 68 # 5-44, Medellin"
    },
    {
      "type": "patient",
      "id": 445567890123,
      "username": "luisa_tc",
      "firstname": "Luisa",
      "lastname": "Torres",
      "password": "Pass@4567",
      "email": "luisa@gmail.com",
      "birthdate": "1995-11-07",
      "gender": false,
      "phone": 3151122334,
      "address": "Calle 72 # 45-20, Cali"
    },
    {
      "type": "patient",
      "id": 556678901234,
      "username": "andres_cv",
      "firstname": "Andres",
      "lastname": "Castro",
      "password": "Pass@5678",
      "email": "andres@gmail.com",
      "birthdate": "2000-06-18",
      "gender": true,
      "phone": 3003344556,
      "address": "Calle 10 # 8-15, Cartagena"
    },
    {
      "type": "patient",
      "id": 667789012345,
      "username": "valentina_mo",
      "firstname": "Valentina",
      "lastname": "Morales",
      "password": "Pass@6789",
      "email": "vmorales@gmail.com",
      "birthdate": "1992-03-25",
      "gender": false,
      "phone": 3184455667,
      "address": "Carrera 15 # 32-60, Bucaramanga"
    },
    {
      "type": "patient",
      "id": 778890123456,
      "username": "sergio_vg",
      "firstname": "Sergio",
      "lastname": "Vargas",
      "password": "Pass@7890",
      "email": "svargas@hotmail.com",
      "birthdate": "1988-09-14",
      "gender": true,
      "phone": 3225566778,
      "address": "Transversal 40 # 20-05, Pereira"
    },
    {
      "type": "patient",
      "id": 889901234567,
      "username": "natalia_pf",
      "firstname": "Natalia",
      "lastname": "Perez",
      "password": "Pass@8901",
      "email": "nperez@gmail.com",
      "birthdate": "1997-12-03",
      "gender": false,
      "phone": 3136677889,
      "address": "Calle 100 # 15-80, Bogota"
    },
    {
      "type": "patient",
      "id": 990012345678,
      "username": "camilo_ar",
      "firstname": "Camilo",
      "lastname": "Arbelaez",
      "password": "Pass@9012",
      "email": "camilo@gmail.com",
      "birthdate": "2001-07-19",
      "gender": true,
      "phone": 3007788990,
      "address": "Carrera 80 # 55-30, Medellin"
    },
    {
      "type": "patient",
      "id": 101123456789,
      "username": "isabella_rm",
      "firstname": "Isabella",
      "lastname": "Rios",
      "password": "Pass@0123",
      "email": "isabella@yahoo.com",
      "birthdate": "1993-02-11",
      "gender": false,
      "phone": 3168899001,
      "address": "Calle 5 # 3-90, Santa Marta"
    },
    {
      "type": "doctor",
      "id": 111234567890,
      "username": "dr_aguirre",
      "firstname": "Diego",
      "lastname": "Aguirre",
      "password": "Doc@1234",
      "specialty": "CARDIOLOGY",
      "licenceNumber": "L-1234567890 MTL",
      "assignedOffice": "O-101"
    },
    {
      "type": "doctor",
      "id": 222345678901,
      "username": "dra_blanco",
      "firstname": "Laura",
      "lastname": "Blanco",
      "password": "Doc@2345",
      "specialty": "NEUROLOGY",
      "licenceNumber": "L-2345678901 MTL",
      "assignedOffice": "O-102"
    },
    {
      "type": "doctor",
      "id": 333456789012,
      "username": "dr_castillo",
      "firstname": "Ricardo",
      "lastname": "Castillo",
      "password": "Doc@3456",
      "specialty": "PEDIATRICS",
      "licenceNumber": "L-3456789012 MTL",
      "assignedOffice": "O-203"
    },
    {
      "type": "doctor",
      "id": 444567890123,
      "username": "dra_duarte",
      "firstname": "Alejandra",
      "lastname": "Duarte",
      "password": "Doc@4567",
      "specialty": "DERMATOLOGY",
      "licenceNumber": "L-4567890123 MTL",
      "assignedOffice": "O-204"
    },
    {
      "type": "doctor",
      "id": 555678901234,
      "username": "dr_escobar",
      "firstname": "Mauricio",
      "lastname": "Escobar",
      "password": "Doc@5678",
      "specialty": "ORTHOPEDICS",
      "licenceNumber": "L-5678901234 MTL",
      "assignedOffice": "O-305"
    },
    {
      "type": "doctor",
      "id": 666789012345,
      "username": "dra_fuentes",
      "firstname": "Gloria",
      "lastname": "Fuentes",
      "password": "Doc@6789",
      "specialty": "GYNECOLOGY",
      "licenceNumber": "L-6789012345 MTL",
      "assignedOffice": "O-306"
    },
    {
      "type": "doctor",
      "id": 777890123456,
      "username": "dr_gomez",
      "firstname": "Felipe",
      "lastname": "Gomez",
      "password": "Doc@7890",
      "specialty": "PSYCHIATRY",
      "licenceNumber": "L-7890123456 MTL",
      "assignedOffice": "O-407"
    },
    {
      "type": "doctor",
      "id": 888901234567,
      "username": "dra_ibarra",
      "firstname": "Patricia",
      "lastname": "Ibarra",
      "password": "Doc@8901",
      "specialty": "ONCOLOGY",
      "licenceNumber": "L-8901234567 MTL",
      "assignedOffice": "O-408"
    }
  ]
}
